chemfiles/__init__.py
chemfiles/_c_api.py
chemfiles/_c_lib.py
chemfiles/atom.py
chemfiles/cell.py
chemfiles/chemfiles.dll
chemfiles/frame.py
chemfiles/misc.py
chemfiles/property.py
chemfiles/residue.py
chemfiles/selection.py
chemfiles/topology.py
chemfiles/trajectory.py
chemfiles/utils.py
chemfiles-0.10.4.dist-info/LICENSE
chemfiles-0.10.4.dist-info/METADATA
chemfiles-0.10.4.dist-info/WHEEL
chemfiles-0.10.4.dist-info/top_level.txt
chemfiles-0.10.4.dist-info/RECORD
