Metadata-Version: 2.1
Name: chemfiles
Version: 0.10.4
Summary: Read and write computational chemistry files
Home-page: http://github.com/chemfiles/chemfiles.py
Author: Guillaume Fraux
Author-email: guillaume@fraux.fr
Keywords: chemistry computational cheminformatics files formats
Classifier: Development Status :: 4 - Beta
Classifier: Environment :: Console
Classifier: Intended Audience :: Developers
Classifier: Intended Audience :: Science/Research
Classifier: License :: OSI Approved :: BSD License
Classifier: Operating System :: MacOS :: MacOS X
Classifier: Operating System :: Microsoft :: Windows
Classifier: Operating System :: Unix
Classifier: Programming Language :: Python :: 2
Classifier: Programming Language :: Python :: 3
Classifier: Topic :: Scientific/Engineering :: Chemistry
Classifier: Topic :: Software Development :: Libraries :: Python Modules
Classifier: Topic :: Utilities
License-File: LICENSE
Requires-Dist: numpy
